mfypublic/__init__.py
mfypublic/baseone.py
mfypublic/basetwo.py
mfypublic/get_log.py
mfypublic/read_data.py
mfypublic-1.1.4.dist-info/LICENSE
mfypublic-1.1.4.dist-info/METADATA
mfypublic-1.1.4.dist-info/WHEEL
mfypublic-1.1.4.dist-info/top_level.txt
mfypublic-1.1.4.dist-info/RECORD
