Metadata-Version: 2.1
Name: mfypublic
Version: 1.1.4
Summary: UNKNOWN
Home-page: https://pypi.org/project/mfypublic
Author: MingFeiyang
Author-email: mfy1102@163.com
License: UNKNOWN
Platform: UNKNOWN
Classifier: Programming Language :: Python :: 3
Requires-Python: >=3.7
License-File: LICENSE
Requires-Dist: Jinja2 (==2.10.1)
Requires-Dist: PyYAML (==5.3.1)
Requires-Dist: requests (==2.24.0)
